MANIFEST.in
README.md
setup.py
badgekit/__init__.py
badgekit/api.py
badgekit/version.py
badgekit_api_client.egg-info/PKG-INFO
badgekit_api_client.egg-info/SOURCES.txt
badgekit_api_client.egg-info/dependency_links.txt
badgekit_api_client.egg-info/not-zip-safe
badgekit_api_client.egg-info/requires.txt
badgekit_api_client.egg-info/top_level.txt
test/__init__.py
test/api_test.py